README.rst
setup.py
sphinxcontrib/__init__.py
sphinxcontrib/websnap/__init__.py
sphinxcontrib/websnap/webpage2html.py
sphinxcontrib/websnap/websnap.py
sphinxcontrib_websnap.egg-info/PKG-INFO
sphinxcontrib_websnap.egg-info/SOURCES.txt
sphinxcontrib_websnap.egg-info/dependency_links.txt
sphinxcontrib_websnap.egg-info/namespace_packages.txt
sphinxcontrib_websnap.egg-info/not-zip-safe
sphinxcontrib_websnap.egg-info/requires.txt
sphinxcontrib_websnap.egg-info/top_level.txt