Metadata-Version: 1.1
Name: sphinxcontrib-websnap
Version: 0.2.0
Summary: Sphinx directives for archiving and linking to websites
Home-page: http://github.com/chriscz/sphinxcontrib-websnap
Author: Chris Coetzee
Author-email: chriscz93@gmail.com
License: MPL
Download-URL: http://pypi.python.org/pypi/sphinxcontrib-websnap
Platform: any
Classifier: Development Status :: 3 - Alpha
Classifier: Environment :: Console
Classifier: Environment :: Web Environment
Classifier: Intended Audience :: Developers
Classifier: License :: OSI Approved :: Mozilla Public License 2.0 (MPL 2.0)
Classifier: Operating System :: OS Independent
Classifier: Programming Language :: Python
Classifier: Topic :: Documentation
Classifier: Topic :: Utilities
